LICENCE
README.md
setup.py
msaSDK/__init__.py
msaSDK/msaapi.py
msaSDK/run.py
msaSDK/security.py
msaSDK/service.py
msaSDK/session.py
msaSDK/userprogress.py
msaSDK.egg-info/PKG-INFO
msaSDK.egg-info/SOURCES.txt
msaSDK.egg-info/dependency_links.txt
msaSDK.egg-info/top_level.txt
msaSDK.egg-info/zip-safe
msaSDK/admin/__init__.py
msaSDK/admin/admin.py
msaSDK/admin/parser.py
msaSDK/admin/site.py
msaSDK/admin/frontend/__init__.py
msaSDK/admin/frontend/components.py
msaSDK/admin/frontend/constants.py
msaSDK/admin/frontend/types.py
msaSDK/admin/frontend/utils.py
msaSDK/admin/utils/__init__.py
msaSDK/admin/utils/choices.py
msaSDK/admin/utils/fields.py
msaSDK/admin/utils/functools.py
msaSDK/admin/utils/translation.py
msaSDK/app/__init__.py
msaSDK/auth/__init__.py
msaSDK/auth/admin.py
msaSDK/auth/app.py
msaSDK/auth/site.py
msaSDK/auth/auth/__init__.py
msaSDK/auth/auth/auth.py
msaSDK/auth/auth/models.py
msaSDK/auth/auth/schemas.py
msaSDK/auth/auth/backends/__init__.py
msaSDK/auth/auth/backends/base.py
msaSDK/auth/auth/backends/db.py
msaSDK/auth/auth/backends/jwt.py
msaSDK/auth/auth/backends/redis.py
msaSDK/models/__init__.py
msaSDK/models/openapi.py
msaSDK/models/service.py
msaSDK/router/__init__.py
msaSDK/router/system.py
msaSDK/services/__init__.py
msaSDK/services/wdc.py